django_odata/__init__.py
django_odata/mixins.py
django_odata/serializers.py
django_odata/utils.py
django_odata/viewsets.py
django_odata-0.1.1.dist-info/licenses/LICENSE
tests/__init__.py
tests/apps.py
tests/conftest.py
tests/settings.py
tests/test_mixins.py
tests/test_serializers.py
tests/test_utils.py
tests/test_viewsets.py
tests/integration/__init__.py
tests/integration/test_odata_comprehensive.py
tests/integration/test_odata_expressions.py
tests/integration/test_odata_integration.py
tests/integration/test_odata_performance.py
tests/integration/support/__init__.py
tests/integration/support/apps.py
tests/integration/support/models.py
tests/integration/support/settings.py
tests/integration/support/urls.py
tests/integration/support/migrations/0001_initial.py
tests/integration/support/migrations/__init__.py
django_odata-0.1.1.dist-info/METADATA
django_odata-0.1.1.dist-info/WHEEL
django_odata-0.1.1.dist-info/top_level.txt
django_odata-0.1.1.dist-info/RECORD
